dragenfly/__init__.py
dragenfly-0.0.1.dist-info/METADATA
dragenfly-0.0.1.dist-info/WHEEL
dragenfly-0.0.1.dist-info/top_level.txt
dragenfly-0.0.1.dist-info/RECORD
