Metadata-Version: 2.1
Name: dragenfly
Version: 0.0.1
Summary: Utilities for Dragen
Home-page: https://github.com/seqfu/dragenfly
Author: Ajay Khanna
Author-email: seqfu@seqfu.org
License: UNKNOWN
Project-URL: Bug Tracker, https://github.com/seqfu/dragenfly/issues
Platform: UNKNOWN
Classifier: Programming Language :: Python :: 3
Classifier: License :: OSI Approved :: MIT License
Classifier: Operating System :: OS Independent
Requires-Python: >=3.6
